{
  "parties" : [ {
    "accountDomicileCountryCode" : "JP",
    "accountID" : "549300I6K0JHSVK8I066",
    "accountName" : "Mizuho Securities Co. Ltd.",
    "alwaysCoveredBondExecution" : false,
    "amfDerivativesDealer" : false,
    "amfSpecialEntity" : false,
    "appropriatenessInfoAndWarnings" : false,
    "asicReportingDelegate" : "N/A",
    "auNexusOptIn" : false,
    "auReportingCounterpartyRepresentation" : null,
    "austrailianFinServicesLicense" : false,
    "australianPhase2ReportingThreshold" : false,
    "authorizedDepositInstitution" : false,
    "branch" : false,
    "bunchedOrder" : false,
    "caCoveredEntity" : false,
    "caFinancialEntity" : false,
    "caFinancialInstitution" : false,
    "caIMPhaseInCategory" : "NotPhasedIn",
    "caMarginExemptAffiliate" : false,
    "capabilities" : [ ],
    "cdeaDocumentation" : true,
    "cftcEndUserMeetsFinancialObligations" : true,
    "cftcFinalUSPerson" : false,
    "cftcForeignOutwardFacingMarginAffiliate" : false,
    "cftcIMPhaseInCategory" : "NotPhasedIn",
    "cftcMajorJurisdiction" : true,
    "cftcSdrDelegate" : "N/A",
    "cftcSegregatedMargin" : "NotApplicable",
    "cftcSwapEntity" : true,
    "clearingImplementationCategory" : "CATEGORY2",
    "clientType" : "Professional",
    "commoditiesCommercialIntent" : false,
    "conduitAffiliateUSPerson" : false,
    "contraparty" : true,
    "creditline" : true,
    "customCptyAttributes" : { },
    "customCptyIdentifiers" : { },
    "defaultNettingSet" : "Netting Set E",
    "designatedFiduciary" : false,
    "disclosureAcknoledgementClearing" : true,
    "disclosureAcknoledgementDailyMarks" : true,
    "disclosureAcknoledgementScenarioAnalysis" : true,
    "disclosureAcknoledgementSpecialEntity" : true,
    "disclosureDistribution" : true,
    "eligibleAffiliateInternalParty" : false,
    "eligibleContractParticipant" : true,
    "eligibleTreasuryAffiliate" : false,
    "emirArticle1_4b_entity" : false,
    "emirCcp" : false,
    "endUser" : "NO",
    "energyOperator" : false,
    "erisaSpecialEntity" : false,
    "erisaSpecialEntitySafeHarborOption1" : false,
    "erisaSpecialEntitySafeHarborOption2" : false,
    "esmaClearingCategory" : "CATEGORY2",
    "esmaClearingCategoryCredit1" : "CATEGORY2",
    "esmaClearingCategoryRates2" : "CATEGORY2",
    "establishedIn" : "JP",
    "euAffiliateStatus" : "NotAffiliate",
    "euCentralBank" : false,
    "euCentralBankOrPublicDebtManager" : false,
    "euExemptedForeignCentralBank" : false,
    "euExemptedPensionScheme" : false,
    "euExemptedPublicSectorEntity" : false,
    "euIMPhaseInCategory" : "NotPhasedIn",
    "euMultilateralDevelopmentBank" : false,
    "euPublicDebtManager" : false,
    "exemptCooperative" : false,
    "exemptForeignLicense" : false,
    "exemptIntragroupAffiliate" : false,
    "fiboTypeI" : true,
    "fieaCentralBank" : false,
    "fieaGovernment" : false,
    "fieaInternalPartyAffiliate" : false,
    "financialCounterparty" : false,
    "financialEntity" : true,
    "financialInstruBusinessOperation2" : true,
    "financialInstrumentBusinessOperation" : true,
    "foreignADI" : false,
    "foreignBranchUSPerson" : false,
    "foreignCentralBank" : false,
    "foreignGovernment" : false,
    "frequentlyUsedCounterparty" : true,
    "fxCommodityPoolOperator" : false,
    "fxEligibleContractParticipant" : true,
    "fxMasterAgreement" : true,
    "fxPhysicalSettlementRepresentation" : false,
    "fxSecuritySettlementRepresentation" : false,
    "guaranteedAffiliateUSPerson" : false,
    "hasIsdaCanadaReportingAgreement" : false,
    "hasMultiJurisSmallCMNotional" : false,
    "hasSmallCMNotional" : false,
    "institutionalSuitabilitySafeHarbor" : false,
    "insuranceRFI" : false,
    "internalPartyAffiliate" : false,
    "internationalFinancialInstitution" : false,
    "intlAuthorityFSA" : false,
    "investmentFirm" : false,
    "isBankRfi" : false,
    "isCAindividual" : false,
    "isGuaranteedByAMFLC" : false,
    "isGuaranteedByMSCLC" : false,
    "isGuaranteedByMultiJurisLC" : false,
    "isGuaranteedByOSCLC" : false,
    "isMbBased" : false,
    "isMultiJurisBased" : false,
    "isOnBased" : false,
    "isQcBased" : false,
    "isda2013ACAInPlace" : false,
    "isdaDFProtocolAugust2012Signed1" : true,
    "isdaDFProtocolMarch2013Signed" : true,
    "isdaEMIRReportingDelegate" : "N/A",
    "isdaMasterAgreement" : true,
    "isdaPBProtocolSigned" : false,
    "japaneseCentralBank" : false,
    "japaneseGovernment" : false,
    "japaneseLocalAuthority" : false,
    "legalEntityID" : "549300I6K0JHSVK8I066",
    "liquidMidWaiverFX" : false,
    "liquidMidWaiverNonFX" : false,
    "majorSwapParticipant" : false,
    "miFID2Exemptions" : [ "NotApplicable" ],
    "mscCrownEntity" : false,
    "mscDerivativesDealer" : false,
    "multiJurisDerivativesDealer" : false,
    "multiJurisSpecialEntity" : false,
    "negAffAgreementProvider" : "NotApplicable",
    "nonERISASpecialEntitySafeHarbor" : false,
    "nonFinancialCounterpartyMinus" : false,
    "nonFinancialCounterpartyPlus" : false,
    "nonJapanCentralBank" : false,
    "nonJapanGovernment" : false,
    "oscCrownEntity" : false,
    "oscDerivativesDealer" : false,
    "parentID" : "",
    "partyRole" : "",
    "portfolioReconciliation" : true,
    "postTradeSuitabilityStatements" : false,
    "primeBrokers" : [ ],
    "quoteDisclosureCategory" : "NotApplicable",
    "registeredFinancialInstitution" : true,
    "ruDelegatedInformingPerson" : "N/A",
    "ruFinancialEntity" : false,
    "russianIndividual" : false,
    "russianLegalEntity" : false,
    "russianMasterAgreement" : false,
    "russianReportingParty" : "CLIENT",
    "secElectionApproval" : false,
    "secIssuerFiler" : false,
    "secUSPerson" : false,
    "securityBasedMajorSwapParticipant" : false,
    "securityBasedSwapDealer" : false,
    "sfcATSCCP" : false,
    "sfcApprovedMoneyBroker" : false,
    "sfcAuthorizedInstitutions" : false,
    "sfcCompany" : false,
    "sfcForeignAuthorizedInstitutions" : false,
    "sfcInitialPhaseIRNotional" : false,
    "sfcInitialPhaseNDFNotional" : false,
    "sfcLicenseDate" : "1/1/15",
    "sfcLicensedCorporations" : false,
    "sfcRCH" : false,
    "sfcReportingAgent" : "N/A",
    "singaporeSpecifiedPerson" : false,
    "smallLocalPresence" : false,
    "specialEntity" : false,
    "standingEndUserExceptionElection" : false,
    "standingOptOutAnnualFiling" : false,
    "substituteLei" : "",
    "suitabilityInfo" : false,
    "swapDealer" : true,
    "thirdCountryEntityFCBranch" : false,
    "thirdCountryEntityFCGuarantee" : false,
    "thirdCountryFirmBranch" : false,
    "usMultilateralDevelopmentBank" : false,
    "usPrudentiallyRegulated" : false,
    "usUnclearedStandingEndUserExceptionElection" : false,
    "usprGuarantorUSPerson" : false,
    "usprIMPhaseInCategory" : "NotPhasedIn",
    "usprUSBranchForeignBank" : false,
    "usprUSPerson" : false,
    "usprUnclearedEndUser" : "NotEndUser",
    "voiceDistributionMidVariableMET" : true
  }, {
    "accountDomicileCountryCode" : "US",
    "accountID" : "549300KWWR4P1RYUVG65",
    "accountName" : "Sears Holding Corporation",
    "alwaysCoveredBondExecution" : false,
    "amfDerivativesDealer" : false,
    "amfSpecialEntity" : false,
    "appropriatenessInfoAndWarnings" : false,
    "asicReportingDelegate" : "N/A",
    "auNexusOptIn" : false,
    "auReportingCounterpartyRepresentation" : null,
    "austrailianFinServicesLicense" : false,
    "australianPhase2ReportingThreshold" : false,
    "authorizedDepositInstitution" : false,
    "branch" : false,
    "bunchedOrder" : false,
    "caCoveredEntity" : false,
    "caFinancialEntity" : false,
    "caFinancialInstitution" : false,
    "caIMPhaseInCategory" : "NotPhasedIn",
    "caMarginExemptAffiliate" : false,
    "capabilities" : [ ],
    "cdeaDocumentation" : true,
    "cftcEndUserMeetsFinancialObligations" : true,
    "cftcFinalUSPerson" : true,
    "cftcForeignOutwardFacingMarginAffiliate" : false,
    "cftcIMPhaseInCategory" : "NotPhasedIn",
    "cftcMajorJurisdiction" : false,
    "cftcSdrDelegate" : "N/A",
    "cftcSegregatedMargin" : "NotApplicable",
    "cftcSwapEntity" : false,
    "clearingImplementationCategory" : "CATEGORY2",
    "clientType" : "Professional",
    "commoditiesCommercialIntent" : false,
    "conduitAffiliateUSPerson" : false,
    "contraparty" : true,
    "creditline" : true,
    "customCptyAttributes" : { },
    "customCptyIdentifiers" : { },
    "defaultNettingSet" : "Netting Set D",
    "designatedFiduciary" : false,
    "disclosureAcknoledgementClearing" : true,
    "disclosureAcknoledgementDailyMarks" : true,
    "disclosureAcknoledgementScenarioAnalysis" : true,
    "disclosureAcknoledgementSpecialEntity" : true,
    "disclosureDistribution" : true,
    "eligibleAffiliateInternalParty" : false,
    "eligibleContractParticipant" : false,
    "eligibleTreasuryAffiliate" : false,
    "emirArticle1_4b_entity" : false,
    "emirCcp" : false,
    "endUser" : "NO",
    "energyOperator" : false,
    "erisaSpecialEntity" : false,
    "erisaSpecialEntitySafeHarborOption1" : false,
    "erisaSpecialEntitySafeHarborOption2" : false,
    "esmaClearingCategory" : "CATEGORY2",
    "esmaClearingCategoryCredit1" : "CATEGORY2",
    "esmaClearingCategoryRates2" : "CATEGORY2",
    "establishedIn" : "US",
    "euAffiliateStatus" : "NotAffiliate",
    "euCentralBank" : false,
    "euCentralBankOrPublicDebtManager" : false,
    "euExemptedForeignCentralBank" : false,
    "euExemptedPensionScheme" : false,
    "euExemptedPublicSectorEntity" : false,
    "euIMPhaseInCategory" : "NotPhasedIn",
    "euMultilateralDevelopmentBank" : false,
    "euPublicDebtManager" : false,
    "exemptCooperative" : false,
    "exemptForeignLicense" : false,
    "exemptIntragroupAffiliate" : false,
    "fiboTypeI" : false,
    "fieaCentralBank" : false,
    "fieaGovernment" : false,
    "fieaInternalPartyAffiliate" : false,
    "financialCounterparty" : false,
    "financialEntity" : false,
    "financialInstruBusinessOperation2" : false,
    "financialInstrumentBusinessOperation" : false,
    "foreignADI" : false,
    "foreignBranchUSPerson" : false,
    "foreignCentralBank" : false,
    "foreignGovernment" : false,
    "frequentlyUsedCounterparty" : true,
    "fxCommodityPoolOperator" : false,
    "fxEligibleContractParticipant" : false,
    "fxMasterAgreement" : true,
    "fxPhysicalSettlementRepresentation" : false,
    "fxSecuritySettlementRepresentation" : false,
    "guaranteedAffiliateUSPerson" : false,
    "hasIsdaCanadaReportingAgreement" : false,
    "hasMultiJurisSmallCMNotional" : false,
    "hasSmallCMNotional" : true,
    "institutionalSuitabilitySafeHarbor" : true,
    "insuranceRFI" : false,
    "internalPartyAffiliate" : false,
    "internationalFinancialInstitution" : false,
    "intlAuthorityFSA" : false,
    "investmentFirm" : false,
    "isBankRfi" : false,
    "isCAindividual" : false,
    "isGuaranteedByAMFLC" : false,
    "isGuaranteedByMSCLC" : false,
    "isGuaranteedByMultiJurisLC" : false,
    "isGuaranteedByOSCLC" : false,
    "isMbBased" : false,
    "isMultiJurisBased" : false,
    "isOnBased" : false,
    "isQcBased" : false,
    "isda2013ACAInPlace" : false,
    "isdaDFProtocolAugust2012Signed1" : true,
    "isdaDFProtocolMarch2013Signed" : true,
    "isdaEMIRReportingDelegate" : "N/A",
    "isdaMasterAgreement" : true,
    "isdaPBProtocolSigned" : false,
    "japaneseCentralBank" : false,
    "japaneseGovernment" : false,
    "japaneseLocalAuthority" : false,
    "legalEntityID" : "549300KWWR4P1RYUVG65",
    "liquidMidWaiverFX" : false,
    "liquidMidWaiverNonFX" : false,
    "majorSwapParticipant" : false,
    "miFID2Exemptions" : [ "NotApplicable" ],
    "mscCrownEntity" : false,
    "mscDerivativesDealer" : false,
    "multiJurisDerivativesDealer" : false,
    "multiJurisSpecialEntity" : false,
    "negAffAgreementProvider" : "NotApplicable",
    "nonERISASpecialEntitySafeHarbor" : false,
    "nonFinancialCounterpartyMinus" : false,
    "nonFinancialCounterpartyPlus" : false,
    "nonJapanCentralBank" : false,
    "nonJapanGovernment" : false,
    "oscCrownEntity" : false,
    "oscDerivativesDealer" : false,
    "parentID" : "",
    "partyRole" : "",
    "portfolioReconciliation" : true,
    "postTradeSuitabilityStatements" : false,
    "primeBrokers" : [ ],
    "quoteDisclosureCategory" : "NotApplicable",
    "registeredFinancialInstitution" : false,
    "ruDelegatedInformingPerson" : "N/A",
    "ruFinancialEntity" : false,
    "russianIndividual" : false,
    "russianLegalEntity" : false,
    "russianMasterAgreement" : false,
    "russianReportingParty" : "CLIENT",
    "secElectionApproval" : false,
    "secIssuerFiler" : false,
    "secUSPerson" : false,
    "securityBasedMajorSwapParticipant" : false,
    "securityBasedSwapDealer" : false,
    "sfcATSCCP" : false,
    "sfcApprovedMoneyBroker" : false,
    "sfcAuthorizedInstitutions" : false,
    "sfcCompany" : false,
    "sfcForeignAuthorizedInstitutions" : false,
    "sfcInitialPhaseIRNotional" : false,
    "sfcInitialPhaseNDFNotional" : false,
    "sfcLicenseDate" : "1/1/15",
    "sfcLicensedCorporations" : false,
    "sfcRCH" : false,
    "sfcReportingAgent" : "N/A",
    "singaporeSpecifiedPerson" : false,
    "smallLocalPresence" : false,
    "specialEntity" : false,
    "standingEndUserExceptionElection" : true,
    "standingOptOutAnnualFiling" : false,
    "substituteLei" : "",
    "suitabilityInfo" : false,
    "swapDealer" : false,
    "thirdCountryEntityFCBranch" : false,
    "thirdCountryEntityFCGuarantee" : false,
    "thirdCountryFirmBranch" : false,
    "usMultilateralDevelopmentBank" : false,
    "usPrudentiallyRegulated" : false,
    "usUnclearedStandingEndUserExceptionElection" : false,
    "usprGuarantorUSPerson" : false,
    "usprIMPhaseInCategory" : "NotPhasedIn",
    "usprUSBranchForeignBank" : false,
    "usprUSPerson" : true,
    "usprUnclearedEndUser" : "FinancialEndUser",
    "voiceDistributionMidVariableMET" : true
  } ]
}